[
  {
    "code": "A",
    "name": "Accord (A)",
    "url": "https://inecnigeria.org/wp-content/uploads/2024/06/A.jpg"
  },
  {
    "code": "AA",
    "name": "Action Alliance (AA)",
    "url": "https://inecnigeria.org/wp-content/uploads/2024/06/AA-150x150-1.jpg"
  },
  {
    "code": "ADP",
    "name": "Action Democratic Party (ADP)",
    "url": "https://inecnigeria.org/wp-content/uploads/2024/06/ADP-150x150-1.png"
  },
  {
    "code": "APP",
    "name": "Action Peoples Party (APP)",
    "url": "https://inecnigeria.org/wp-content/uploads/2024/06/APP-150x114-2.png"
  },
  {
    "code": "AAC",
    "name": "African Action Congress (AAC)",
    "url": "https://inecnigeria.org/wp-content/uploads/2024/06/AAC.jpg"
  },
  {
    "code": "ADC",
    "name": "African Democratic Congress (ADC)",
    "url": "https://inecnigeria.org/wp-content/uploads/2024/06/ADC-150x150-1.jpg"
  },
  {
    "code": "APC",
    "name": "All Progressives Congress (APC)",
    "url": "https://inecnigeria.org/wp-content/uploads/2024/06/apclogo-150x150-2.jpg"
  },
  {
    "code": "APGA",
    "name": "All Progressives Grand Alliance (APGA)",
    "url": "https://inecnigeria.org/wp-content/uploads/2024/06/APGA-150x140-2.jpg"
  },
  {
    "code": "APM",
    "name": "Allied Peoples Movement (APM)",
    "url": "https://inecnigeria.org/wp-content/uploads/2024/06/APM-150x117-2.jpg"
  },
  {
    "code": "BP",
    "name": "Boot Party (BP)",
    "url": "https://inecnigeria.org/wp-content/uploads/2024/06/BootParty-150x150-1.jpg"
  },
  {
    "code": "DLA",
    "name": "DEMOCRATIC LEADERSHIP ALLIANCE (DLA)",
    "url": "https://inecnigeria.org/wp-content/uploads/logo-DLA.jpg"
  },
  {
    "code": "LP",
    "name": "Labour Party (LP)",
    "url": "https://inecnigeria.org/wp-content/uploads/2024/06/LP-150x150-1.jpg"
  },
  {
    "code": "NRM",
    "name": "National Rescue Movement (NRM)",
    "url": "https://inecnigeria.org/wp-content/uploads/2024/06/NRM-150x150-1.png"
  },
  {
    "code": "NNPP",
    "name": "New Nigeria Peoples Party (NNPP)",
    "url": "https://inecnigeria.org/wp-content/uploads/2024/06/nnpp-1.jpg"
  },
  {
    "code": "PDP",
    "name": "Peoples Democratic Party (PDP)",
    "url": "https://inecnigeria.org/wp-content/uploads/2024/06/PDP-150x150-1.jpg"
  },
  {
    "code": "PRP",
    "name": "Peoples Redemption Party (PRP)",
    "url": "https://inecnigeria.org/wp-content/uploads/2024/06/PRP.png"
  },
  {
    "code": "SDP",
    "name": "Social Democratic Party (SDP)",
    "url": "https://inecnigeria.org/wp-content/uploads/2024/06/SDP-150x150-1.png"
  },
  {
    "code": "YPP",
    "name": "Young Progressive Party (YPP)",
    "url": "https://inecnigeria.org/wp-content/uploads/2024/06/YPP-150x150-1.png"
  },
  {
    "code": "YP",
    "name": "Youth Party (YP)",
    "url": "https://inecnigeria.org/wp-content/uploads/2024/06/Screenshot-2023-07-12-at-4.33.10-PM-150x150-1.png"
  },
  {
    "code": "ZLP",
    "name": "Zenith Labour Party (ZLP)",
    "url": "https://inecnigeria.org/wp-content/uploads/2024/06/ZLP.jpg"
  }
]